{"v":"5.6.2","fr":24,"ip":0,"op":48,"w":1024,"h":1024,"nm":"pig_face","ddd":0,"assets":[{"id":"comp_0","layers":[{"ddd":0,"ind":1,"ty":4,"nm":"Ear_R","parent":7,"sr":1,"ks":{"o":{"a":0,"k":100,"ix":11},"r":{"a":1,"k":[{"i":{"x":[0.667],"y":[1]},"o":{"x":[0.333],"y":[0]},"t":0,"s":[0]},{"i":{"x":[0.667],"y":[1]},"o":{"x":[0.333],"y":[0]},"t":4,"s":[-12]},{"i":{"x":[0.667],"y":[1]},"o":{"x":[0.333],"y":[0]},"t":8,"s":[0]},{"i":{"x":[0.667],"y":[1]},"o":{"x":[0.333],"y":[0]},"t":12,"s":[0]},{"i":{"x":[0.667],"y":[1]},"o":{"x":[0.333],"y":[0]},"t":16,"s":[-6]},{"i":{"x":[0.667],"y":[1]},"o":{"x":[0.333],"y":[0]},"t":20,"s":[0]},{"t":32,"s":[0]}],"ix":10},"p":{"a":0,"k":[-91.784,-287.367,0],"ix":2},"a":{"a":0,"k":[136,-74,0],"ix":1},"s":{"a":0,"k":[100,100,100],"ix":6}},"ao":0,"shapes":[{"ty":"gr","it":[{"ind":0,"ty":"sh","ix":1,"ks":{"a":0,"k":{"i":[[19.987,-19.109],[0,-68.931],[12.978,86.606],[-142.245,-108.543],[0,0]],"o":[[-80.977,77.412],[0,149.89],[-20.266,-135.43],[0,0],[-57.128,-65.779]],"v":[[-4.576,-145.41],[-137.718,-11.149],[5.254,111.437],[128.941,-69.439],[137.718,-73.101]],"c":true},"ix":2},"nm":"Path 1","mn":"ADBE Vector Shape - Group","hd":false},{"ty":"gf","o":{"a":0,"k":100,"ix":10},"r":1,"bm":0,"g":{"p":3,"k":{"a":0,"k":[0,1,0.62,0.71,0.3,1,0.7,0.771,0.739,1,0.78,0.831],"ix":9}},"s":{"a":0,"k":[-41.407,163.178],"ix":5},"e":{"a":0,"k":[0.077,-96.179],"ix":6},"t":1,"nm":"Pigf01","mn":"ADBE Vector Graphic - G-Fill","hd":false},{"ty":"tr","p":{"a":0,"k":[0,0],"ix":2},"a":{"a":0,"k":[0,0],"ix":1},"s":{"a":0,"k":[100,100],"ix":3},"r":{"a":0,"k":0,"ix":6},"o":{"a":0,"k":100,"ix":7},"sk":{"a":0,"k":0,"ix":4},"sa":{"a":0,"k":0,"ix":5},"nm":"Transform"}],"nm":"Shape","np":2,"cix":2,"bm":0,"ix":1,"mn":"ADBE Vector Group","hd":false}],"ip":0,"op":48,"st":0,"bm":0},{"ddd":0,"ind":2,"ty":4,"nm":"Ear_L","parent":7,"sr":1,"ks":{"o":{"a":0,"k":100,"ix":11},"r":{"a":1,"k":[{"i":{"x":[0.667],"y":[1]},"o":{"x":[0.333],"y":[0]},"t":0,"s":[0]},{"i":{"x":[0.667],"y":[1]},"o":{"x":[0.333],"y":[0]},"t":4,"s":[12]},{"i":{"x":[0.667],"y":[1]},"o":{"x":[0.333],"y":[0]},"t":8,"s":[0]},{"i":{"x":[0.667],"y":[1]},"o":{"x":[0.333],"y":[0]},"t":12,"s":[0]},{"i":{"x":[0.667],"y":[1]},"o":{"x":[0.333],"y":[0]},"t":16,"s":[6]},{"i":{"x":[0.667],"y":[1]},"o":{"x":[0.333],"y":[0]},"t":20,"s":[0]},{"t":32,"s":[0]}],"ix":10},"p":{"a":0,"k":[79.78,-287.367,0],"ix":2},"a":{"a":0,"k":[-136,-74,0],"ix":1},"s":{"a":0,"k":[100,100,100],"ix":6}},"ao":0,"shapes":[{"ty":"gr","it":[{"ind":0,"ty":"sh","ix":1,"ks":{"a":0,"k":{"i":[[-19.987,-19.109],[0,-68.931],[-12.978,86.606],[142.245,-108.543],[0,0]],"o":[[80.978,77.412],[0,149.89],[20.265,-135.43],[0,0],[57.128,-65.779]],"v":[[4.576,-145.41],[137.718,-11.149],[-5.254,111.437],[-128.941,-69.439],[-137.718,-73.101]],"c":true},"ix":2},"nm":"Path 1","mn":"ADBE Vector Shape - Group","hd":false},{"ty":"gf","o":{"a":0,"k":100,"ix":10},"r":1,"bm":0,"g":{"p":3,"k":{"a":0,"k":[0,1,0.62,0.71,0.3,1,0.7,0.771,0.739,1,0.78,0.831],"ix":9}},"s":{"a":0,"k":[-0.782,151.131],"ix":5},"e":{"a":0,"k":[-0.782,-152.021],"ix":6},"t":1,"nm":"Pigf02","mn":"ADBE Vector Graphic - G-Fill","hd":false},{"ty":"tr","p":{"a":0,"k":[0,0],"ix":2},"a":{"a":0,"k":[0,0],"ix":1},"s":{"a":0,"k":[100,100],"ix":3},"r":{"a":0,"k":0,"ix":6},"o":{"a":0,"k":100,"ix":7},"sk":{"a":0,"k":0,"ix":4},"sa":{"a":0,"k":0,"ix":5},"nm":"Transform"}],"nm":"Shape","np":2,"cix":2,"bm":0,"ix":1,"mn":"ADBE Vector Group","hd":false}],"ip":0,"op":48,"st":0,"bm":0},{"ddd":0,"ind":3,"ty":4,"nm":"Nose","parent":7,"sr":1,"ks":{"o":{"a":0,"k":100,"ix":11},"r":{"a":0,"k":0,"ix":10},"p":{"a":1,"k":[{"i":{"x":0.667,"y":0.667},"o":{"x":0.333,"y":0.333},"t":0,"s":[-5.997,147.605,0],"to":[0,0,0],"ti":[0,0,0]},{"i":{"x":0.667,"y":1},"o":{"x":0.333,"y":0},"t":2,"s":[-5.997,147.605,0],"to":[0,-6.667,0],"ti":[0,6.667,0]},{"i":{"x":0.667,"y":0.667},"o":{"x":0.333,"y":0.333},"t":6,"s":[-5.997,107.605,0],"to":[0,0,0],"ti":[0,0,0]},{"i":{"x":0.667,"y":1},"o":{"x":0.333,"y":0},"t":9,"s":[-5.997,107.605,0],"to":[0,6.667,0],"ti":[0,0,0]},{"i":{"x":0.667,"y":1},"o":{"x":0.333,"y":0},"t":14,"s":[-5.997,147.605,0],"to":[0,0,0],"ti":[0,0,0]},{"i":{"x":0,"y":1},"o":{"x":0.333,"y":0},"t":22,"s":[-5.997,107.605,0],"to":[0,0,0],"ti":[0,-6.667,0]},{"t":37,"s":[-5.997,147.605,0]}],"ix":2},"a":{"a":0,"k":[512.004,689.84,0],"ix":1},"s":{"a":0,"k":[100,100,100],"ix":6}},"ao":0,"shapes":[{"ty":"gr","it":[{"ty":"gr","it":[{"ind":0,"ty":"sh","ix":1,"ks":{"a":0,"k":{"i":[[-32.262,-32.619],[13.619,38.546]],"o":[[24.272,24.569],[-18.994,-53.677]],"v":[[-14.409,12.552],[21.291,-1.727]],"c":true},"ix":2},"nm":"Path 1","mn":"ADBE Vector Shape - Group","hd":false},{"ty":"fl","c":{"a":0,"k":[0.43137255311,0.207843139768,0.258823543787,1],"ix":4},"o":{"a":0,"k":100,"ix":5},"r":1,"bm":0,"nm":"Fill 1","mn":"ADBE Vector Graphic - Fill","hd":false},{"ty":"tr","p":{"a":0,"k":[558.829,689.994],"ix":2},"a":{"a":0,"k":[0,0],"ix":1},"s":{"a":0,"k":[100,100],"ix":3},"r":{"a":0,"k":0,"ix":6},"o":{"a":0,"k":100,"ix":7},"sk":{"a":0,"k":0,"ix":4},"sa":{"a":0,"k":0,"ix":5},"nm":"Transform"}],"nm":"Group 1","np":2,"cix":2,"bm":0,"ix":1,"mn":"ADBE Vector Group","hd":false},{"ty":"gr","it":[{"ind":0,"ty":"sh","ix":1,"ks":{"a":0,"k":{"i":[[32.274,-32.619],[-13.631,38.546]],"o":[[-24.272,24.569],[18.995,-53.677]],"v":[[14.409,12.552],[-21.292,-1.727]],"c":true},"ix":2},"nm":"Path 1","mn":"ADBE Vector Shape - Group","hd":false},{"ty":"fl","c":{"a":0,"k":[0.43137255311,0.207843139768,0.258823543787,1],"ix":4},"o":{"a":0,"k":100,"ix":5},"r":1,"bm":0,"nm":"Fill 1","mn":"ADBE Vector Graphic - Fill","hd":false},{"ty":"tr","p":{"a":0,"k":[466.43,689.994],"ix":2},"a":{"a":0,"k":[0,0],"ix":1},"s":{"a":0,"k":[100,100],"ix":3},"r":{"a":0,"k":0,"ix":6},"o":{"a":0,"k":100,"ix":7},"sk":{"a":0,"k":0,"ix":4},"sa":{"a":0,"k":0,"ix":5},"nm":"Transform"}],"nm":"Group 2","np":2,"cix":2,"bm":0,"ix":2,"mn":"ADBE Vector Group","hd":false},{"ty":"tr","p":{"a":0,"k":[466.43,689.994],"ix":2},"a":{"a":0,"k":[466.43,689.994],"ix":1},"s":{"a":0,"k":[100,100],"ix":3},"r":{"a":0,"k":0,"ix":6},"o":{"a":0,"k":100,"ix":7},"sk":{"a":0,"k":0,"ix":4},"sa":{"a":0,"k":0,"ix":5},"nm":"Transform"}],"nm":"Group 1","np":2,"cix":2,"bm":0,"ix":1,"mn":"ADBE Vector Group","hd":false},{"ty":"gr","it":[{"ind":0,"ty":"sh","ix":1,"ks":{"a":0,"k":{"i":[[67.915,0],[-9.152,-47.692],[-22.141,0],[-11.899,62.086]],"o":[[-67.866,0],[11.901,62.086],[22.179,0],[9.14,-47.692]],"v":[[-0.017,-84.972],[-111.852,46.639],[-0.017,76.729],[111.855,46.639]],"c":true},"ix":2},"nm":"Path 1","mn":"ADBE Vector Shape - Group","hd":false},{"ty":"gf","o":{"a":0,"k":100,"ix":10},"r":1,"bm":0,"g":{"p":3,"k":{"a":0,"k":[0,0.851,0.4,0.498,0.345,0.925,0.48,0.578,1,1,0.561,0.659],"ix":9}},"s":{"a":0,"k":[-0.004,84.16],"ix":5},"e":{"a":0,"k":[-0.004,-85.784],"ix":6},"t":1,"nm":"Pigf03","mn":"ADBE Vector Graphic - G-Fill","hd":false},{"ty":"tr","p":{"a":0,"k":[512.004,689.84],"ix":2},"a":{"a":0,"k":[0,0],"ix":1},"s":{"a":0,"k":[100,100],"ix":3},"r":{"a":0,"k":0,"ix":6},"o":{"a":0,"k":100,"ix":7},"sk":{"a":0,"k":0,"ix":4},"sa":{"a":0,"k":0,"ix":5},"nm":"Transform"}],"nm":"Group 2","np":2,"cix":2,"bm":0,"ix":2,"mn":"ADBE Vector Group","hd":false}],"ip":0,"op":48,"st":0,"bm":0},{"ddd":0,"ind":4,"ty":4,"nm":"Mouth","parent":3,"sr":1,"ks":{"o":{"a":0,"k":100,"ix":11},"r":{"a":0,"k":0,"ix":10},"p":{"a":1,"k":[{"i":{"x":0.833,"y":0.833},"o":{"x":0.333,"y":0},"t":0,"s":[512.006,763.14,0],"to":[0,-6.667,0],"ti":[0,0,0]},{"i":{"x":0,"y":1},"o":{"x":0.167,"y":0.167},"t":4,"s":[512.006,723.14,0],"to":[0,0,0],"ti":[0,-6.667,0]},{"i":{"x":0.667,"y":0.667},"o":{"x":0.333,"y":0.333},"t":9,"s":[512.006,763.14,0],"to":[0,0,0],"ti":[0,0,0]},{"i":{"x":0.833,"y":0.833},"o":{"x":0.333,"y":0},"t":14,"s":[512.006,763.14,0],"to":[0,-6.667,0],"ti":[0,0,0]},{"i":{"x":0,"y":1},"o":{"x":0.167,"y":0.167},"t":20,"s":[512.006,723.14,0],"to":[0,0,0],"ti":[0,-6.667,0]},{"t":27,"s":[512.006,763.14,0]}],"ix":2},"a":{"a":0,"k":[512.006,763.14,0],"ix":1},"s":{"a":0,"k":[100,100,100],"ix":6}},"ao":0,"shapes":[{"ty":"gr","it":[{"ty":"gr","it":[{"ind":0,"ty":"sh","ix":1,"ks":{"a":0,"k":{"i":[[-2.058,17.65],[0,0],[-2.19,-18.498]],"o":[[2.204,-18.498],[0,0],[2.07,17.65]],"v":[[43.097,-1.374],[0.048,-8.274],[-43.098,-1.374]],"c":true},"ix":2},"nm":"Path 1","mn":"ADBE Vector Shape - Group","hd":false},{"ty":"fl","c":{"a":0,"k":[0.929411768913,0.443137258291,0.588235318661,1],"ix":4},"o":{"a":0,"k":100,"ix":5},"r":1,"bm":0,"nm":"Fill 1","mn":"ADBE Vector Graphic - Fill","hd":false},{"ty":"tr","p":{"a":0,"k":[0,0],"ix":2},"a":{"a":0,"k":[0,0],"ix":1},"s":{"a":0,"k":[100,100],"ix":3},"r":{"a":0,"k":0,"ix":6},"o":{"a":0,"k":100,"ix":7},"sk":{"a":0,"k":0,"ix":4},"sa":{"a":0,"k":0,"ix":5},"nm":"Transform"}],"nm":"Group 1","np":2,"cix":2,"bm":0,"ix":1,"mn":"ADBE Vector Group","hd":false},{"ty":"tr","p":{"a":0,"k":[512,792.088],"ix":2},"a":{"a":0,"k":[0,0],"ix":1},"s":{"a":0,"k":[100,100],"ix":3},"r":{"a":0,"k":0,"ix":6},"o":{"a":0,"k":100,"ix":7},"sk":{"a":0,"k":0,"ix":4},"sa":{"a":0,"k":0,"ix":5},"nm":"Transform"}],"nm":"Group 1","np":1,"cix":2,"bm":0,"ix":1,"mn":"ADBE Vector Group","hd":false},{"ty":"gr","it":[{"ind":0,"ty":"sh","ix":1,"ks":{"a":0,"k":{"i":[[0,-48.878],[0,86.721]],"o":[[0,86.721],[0,-48.878]],"v":[[-97.169,-14.191],[97.169,-14.191]],"c":true},"ix":2},"nm":"Path 1","mn":"ADBE Vector Shape - Group","hd":false},{"ty":"fl","c":{"a":0,"k":[0.101960785687,0.086274512112,0.149019613862,1],"ix":4},"o":{"a":0,"k":100,"ix":5},"r":1,"bm":0,"nm":"Fill 1","mn":"ADBE Vector Graphic - Fill","hd":false},{"ty":"tr","p":{"a":0,"k":[512.006,763.14],"ix":2},"a":{"a":0,"k":[0,0],"ix":1},"s":{"a":0,"k":[100,100],"ix":3},"r":{"a":0,"k":0,"ix":6},"o":{"a":0,"k":100,"ix":7},"sk":{"a":0,"k":0,"ix":4},"sa":{"a":0,"k":0,"ix":5},"nm":"Transform"}],"nm":"Group 2","np":2,"cix":2,"bm":0,"ix":2,"mn":"ADBE Vector Group","hd":false}],"ip":0,"op":48,"st":0,"bm":0},{"ddd":0,"ind":5,"ty":4,"nm":"Eyes","parent":3,"sr":1,"ks":{"o":{"a":0,"k":100,"ix":11},"r":{"a":0,"k":0,"ix":10},"p":{"a":0,"k":[512,545.613,0],"ix":2},"a":{"a":0,"k":[512,545.613,0],"ix":1},"s":{"a":0,"k":[100,100,100],"ix":6}},"ao":0,"shapes":[{"ty":"gr","it":[{"ind":0,"ty":"sh","ix":1,"ks":{"a":1,"k":[{"i":{"x":0.833,"y":0.833},"o":{"x":0.333,"y":0},"t":0,"s":[{"i":[[54.575,0],[-5.218,-39.205],[-0.161,-0.504],[0,1.971],[-43.073,0],[0,-39.247],[0.392,-2.267],[-0.098,0.748]],"o":[[-59.766,0],[0.07,0.523],[-0.23,-1.985],[0,-39.247],[43.074,0],[0,2.112],[0.283,-0.709],[5.557,-42.426]],"v":[[0.004,-45.825],[-77.935,43.644],[-77.575,45.183],[-77.935,39.243],[0.004,-31.861],[77.967,39.243],[77.37,45.825],[77.967,43.644]],"c":true}]},{"i":{"x":0,"y":1},"o":{"x":0.167,"y":0.167},"t":3,"s":[{"i":[[54.575,0],[-5.218,-39.205],[-0.161,-0.504],[0.056,-1.971],[-43.073,0],[3.116,26.772],[0.392,-2.267],[-0.098,0.748]],"o":[[-59.766,0],[0.07,0.523],[-0.23,-1.985],[-0.983,34.272],[43.074,0],[-0.244,-2.098],[0.283,-0.709],[5.557,-42.426]],"v":[[0.004,-45.825],[-77.935,43.644],[-77.575,45.183],[-77.935,39.244],[0.007,111.139],[77.967,39.244],[77.37,45.825],[77.967,43.644]],"c":true}]},{"t":9,"s":[{"i":[[54.575,0],[-5.218,-39.205],[-0.161,-0.504],[0,1.971],[-43.073,0],[0,-39.247],[0.392,-2.267],[-0.098,0.748]],"o":[[-59.766,0],[0.07,0.523],[-0.23,-1.985],[0,-39.247],[43.074,0],[0,2.112],[0.283,-0.709],[5.557,-42.426]],"v":[[0.004,-45.825],[-77.935,43.644],[-77.575,45.183],[-77.935,39.243],[0.004,-31.861],[77.967,39.243],[77.37,45.825],[77.967,43.644]],"c":true}]}],"ix":2},"nm":"Path 1","mn":"ADBE Vector Shape - Group","hd":false},{"ty":"fl","c":{"a":0,"k":[0.709803938866,0.40000000596,0.478431373835,1],"ix":4},"o":{"a":0,"k":100,"ix":5},"r":1,"bm":0,"nm":"Fill 1","mn":"ADBE Vector Graphic - Fill","hd":false},{"ty":"tr","p":{"a":0,"k":[668.417,513.339],"ix":2},"a":{"a":0,"k":[0,0],"ix":1},"s":{"a":0,"k":[100,100],"ix":3},"r":{"a":0,"k":0,"ix":6},"o":{"a":0,"k":100,"ix":7},"sk":{"a":0,"k":0,"ix":4},"sa":{"a":0,"k":0,"ix":5},"nm":"Transform"}],"nm":"Group 1","np":2,"cix":2,"bm":0,"ix":1,"mn":"ADBE Vector Group","hd":false},{"ty":"gr","it":[{"ind":0,"ty":"sh","ix":1,"ks":{"a":1,"k":[{"i":{"x":0.833,"y":0.833},"o":{"x":0.333,"y":0},"t":0,"s":[{"i":[[59.744,0],[-5.557,-42.426],[-0.282,-0.709],[0,2.111],[-43.073,0],[0,-39.247],[0.23,-1.986],[-0.07,0.524]],"o":[[-54.598,0],[0.098,0.747],[-0.392,-2.266],[0,-39.247],[43.073,0],[0,1.972],[0.161,-0.505],[5.218,-39.205]],"v":[[-0.004,-45.824],[-77.966,43.645],[-77.37,45.824],[-77.966,39.244],[-0.027,-31.86],[77.935,39.244],[77.575,45.185],[77.935,43.645]],"c":true}]},{"i":{"x":0,"y":1},"o":{"x":0.167,"y":0.167},"t":3,"s":[{"i":[[59.744,0],[-5.557,-42.426],[-0.282,-0.709],[0.195,-2.102],[-43.073,0],[3.984,33.772],[0.23,-1.986],[-0.07,0.524]],"o":[[-54.598,0],[0.098,0.747],[-0.392,-2.266],[-2.616,28.272],[43.073,0],[-0.231,-1.958],[0.161,-0.505],[5.218,-39.205]],"v":[[-0.004,-45.824],[-77.966,43.645],[-77.37,45.824],[-77.966,39.244],[-0.055,111.64],[77.935,39.244],[77.575,45.185],[77.935,43.645]],"c":true}]},{"t":9,"s":[{"i":[[59.744,0],[-5.557,-42.426],[-0.282,-0.709],[0,2.111],[-43.073,0],[0,-39.247],[0.23,-1.986],[-0.07,0.524]],"o":[[-54.598,0],[0.098,0.747],[-0.392,-2.266],[0,-39.247],[43.073,0],[0,1.972],[0.161,-0.505],[5.218,-39.205]],"v":[[-0.004,-45.824],[-77.966,43.645],[-77.37,45.824],[-77.966,39.244],[-0.027,-31.86],[77.935,39.244],[77.575,45.185],[77.935,43.645]],"c":true}]}],"ix":2},"nm":"Path 1","mn":"ADBE Vector Shape - Group","hd":false},{"ty":"fl","c":{"a":0,"k":[0.709803938866,0.40000000596,0.478431373835,1],"ix":4},"o":{"a":0,"k":100,"ix":5},"r":1,"bm":0,"nm":"Fill 1","mn":"ADBE Vector Graphic - Fill","hd":false},{"ty":"tr","p":{"a":0,"k":[355.582,513.338],"ix":2},"a":{"a":0,"k":[0,0],"ix":1},"s":{"a":0,"k":[100,100],"ix":3},"r":{"a":0,"k":0,"ix":6},"o":{"a":0,"k":100,"ix":7},"sk":{"a":0,"k":0,"ix":4},"sa":{"a":0,"k":0,"ix":5},"nm":"Transform"}],"nm":"Group 2","np":2,"cix":2,"bm":0,"ix":2,"mn":"ADBE Vector Group","hd":false},{"ty":"gr","it":[{"ty":"gr","it":[{"ind":0,"ty":"sh","ix":1,"ks":{"a":0,"k":{"i":[[0,-20.598],[0,20.568]],"o":[[0,20.568],[0,-20.598]],"v":[[-15.877,0.011],[15.877,0.011]],"c":true},"ix":2},"nm":"Path 1","mn":"ADBE Vector Shape - Group","hd":false},{"ty":"fl","c":{"a":0,"k":[1,1,1,1],"ix":4},"o":{"a":0,"k":100,"ix":5},"r":1,"bm":0,"nm":"Fill 1","mn":"ADBE Vector Graphic - Fill","hd":false},{"ty":"tr","p":{"a":0,"k":[383.561,523.572],"ix":2},"a":{"a":0,"k":[0,0],"ix":1},"s":{"a":0,"k":[100,100],"ix":3},"r":{"a":0,"k":0,"ix":6},"o":{"a":0,"k":100,"ix":7},"sk":{"a":0,"k":0,"ix":4},"sa":{"a":0,"k":0,"ix":5},"nm":"Transform"}],"nm":"Group 1","np":2,"cix":2,"bm":0,"ix":1,"mn":"ADBE Vector Group","hd":false},{"ty":"gr","it":[{"ind":0,"ty":"sh","ix":1,"ks":{"a":0,"k":{"i":[[32.167,0],[0,-31.252],[-32.165,0],[0,31.246]],"o":[[-32.165,0],[0,31.246],[32.167,0],[0,-31.252]],"v":[[0.012,-56.601],[-58.206,0.012],[0.012,56.601],[58.206,0.012]],"c":true},"ix":2},"nm":"Path 1","mn":"ADBE Vector Shape - Group","hd":false},{"ty":"fl","c":{"a":0,"k":[0.101960785687,0.086274512112,0.149019613862,1],"ix":4},"o":{"a":0,"k":100,"ix":5},"r":1,"bm":0,"nm":"Fill 1","mn":"ADBE Vector Graphic - Fill","hd":false},{"ty":"tr","p":{"a":0,"k":[363.047,551.875],"ix":2},"a":{"a":0,"k":[0,0],"ix":1},"s":{"a":0,"k":[100,100],"ix":3},"r":{"a":0,"k":0,"ix":6},"o":{"a":0,"k":100,"ix":7},"sk":{"a":0,"k":0,"ix":4},"sa":{"a":0,"k":0,"ix":5},"nm":"Transform"}],"nm":"Group 2","np":2,"cix":2,"bm":0,"ix":2,"mn":"ADBE Vector Group","hd":false},{"ty":"tr","p":{"a":0,"k":[363.047,551.875],"ix":2},"a":{"a":0,"k":[363.047,551.875],"ix":1},"s":{"a":0,"k":[100,100],"ix":3},"r":{"a":0,"k":0,"ix":6},"o":{"a":0,"k":100,"ix":7},"sk":{"a":0,"k":0,"ix":4},"sa":{"a":0,"k":0,"ix":5},"nm":"Transform"}],"nm":"Group 3","np":2,"cix":2,"bm":0,"ix":3,"mn":"ADBE Vector Group","hd":false},{"ty":"gr","it":[{"ind":0,"ty":"sh","ix":1,"ks":{"a":0,"k":{"i":[[-43.073,0],[0,-39.247],[43.073,0],[0,27.766]],"o":[[43.073,0],[0,33.933],[-43.073,0],[0,-39.247]],"v":[[-0.012,-71.117],[77.95,-0.012],[-0.012,71.117],[-77.95,-0.012]],"c":true},"ix":2},"nm":"Path 1","mn":"ADBE Vector Shape - Group","hd":false},{"ty":"fl","c":{"a":0,"k":[1,1,1,1],"ix":4},"o":{"a":0,"k":100,"ix":5},"r":1,"bm":0,"nm":"Fill 1","mn":"ADBE Vector Graphic - Fill","hd":false},{"ty":"tr","p":{"a":0,"k":[355.566,552.595],"ix":2},"a":{"a":0,"k":[0,0],"ix":1},"s":{"a":0,"k":[100,100],"ix":3},"r":{"a":0,"k":0,"ix":6},"o":{"a":0,"k":100,"ix":7},"sk":{"a":0,"k":0,"ix":4},"sa":{"a":0,"k":0,"ix":5},"nm":"Transform"}],"nm":"Group 4","np":2,"cix":2,"bm":0,"ix":4,"mn":"ADBE Vector Group","hd":false},{"ty":"gr","it":[{"ty":"gr","it":[{"ind":0,"ty":"sh","ix":1,"ks":{"a":0,"k":{"i":[[0,-20.598],[0,20.568]],"o":[[0,20.568],[0,-20.598]],"v":[[15.877,0.011],[-15.877,0.011]],"c":true},"ix":2},"nm":"Path 1","mn":"ADBE Vector Shape - Group","hd":false},{"ty":"fl","c":{"a":0,"k":[1,1,1,1],"ix":4},"o":{"a":0,"k":100,"ix":5},"r":1,"bm":0,"nm":"Fill 1","mn":"ADBE Vector Graphic - Fill","hd":false},{"ty":"tr","p":{"a":0,"k":[640.439,523.572],"ix":2},"a":{"a":0,"k":[0,0],"ix":1},"s":{"a":0,"k":[100,100],"ix":3},"r":{"a":0,"k":0,"ix":6},"o":{"a":0,"k":100,"ix":7},"sk":{"a":0,"k":0,"ix":4},"sa":{"a":0,"k":0,"ix":5},"nm":"Transform"}],"nm":"Group 1","np":2,"cix":2,"bm":0,"ix":1,"mn":"ADBE Vector Group","hd":false},{"ty":"gr","it":[{"ind":0,"ty":"sh","ix":1,"ks":{"a":0,"k":{"i":[[-32.165,0],[0,-31.252],[32.167,0],[0,31.246]],"o":[[32.167,0],[0,31.246],[-32.165,0],[0,-31.252]],"v":[[0.006,-56.601],[58.2,0.012],[0.006,56.601],[-58.2,0.012]],"c":true},"ix":2},"nm":"Path 1","mn":"ADBE Vector Shape - Group","hd":false},{"ty":"fl","c":{"a":0,"k":[0.101960785687,0.086274512112,0.149019613862,1],"ix":4},"o":{"a":0,"k":100,"ix":5},"r":1,"bm":0,"nm":"Fill 1","mn":"ADBE Vector Graphic - Fill","hd":false},{"ty":"tr","p":{"a":0,"k":[660.934,551.875],"ix":2},"a":{"a":0,"k":[0,0],"ix":1},"s":{"a":0,"k":[100,100],"ix":3},"r":{"a":0,"k":0,"ix":6},"o":{"a":0,"k":100,"ix":7},"sk":{"a":0,"k":0,"ix":4},"sa":{"a":0,"k":0,"ix":5},"nm":"Transform"}],"nm":"Group 2","np":2,"cix":2,"bm":0,"ix":2,"mn":"ADBE Vector Group","hd":false},{"ty":"tr","p":{"a":0,"k":[660.934,551.875],"ix":2},"a":{"a":0,"k":[660.934,551.875],"ix":1},"s":{"a":0,"k":[100,100],"ix":3},"r":{"a":0,"k":0,"ix":6},"o":{"a":0,"k":100,"ix":7},"sk":{"a":0,"k":0,"ix":4},"sa":{"a":0,"k":0,"ix":5},"nm":"Transform"}],"nm":"Group 5","np":2,"cix":2,"bm":0,"ix":5,"mn":"ADBE Vector Group","hd":false},{"ty":"gr","it":[{"ind":0,"ty":"sh","ix":1,"ks":{"a":0,"k":{"i":[[43.074,0],[0,-39.247],[-43.073,0],[0,27.766]],"o":[[-43.073,0],[0,33.933],[43.074,0],[0,-39.247]],"v":[[-0.012,-71.117],[-77.951,-0.012],[-0.012,71.117],[77.951,-0.012]],"c":true},"ix":2},"nm":"Path 1","mn":"ADBE Vector Shape - Group","hd":false},{"ty":"fl","c":{"a":0,"k":[1,1,1,1],"ix":4},"o":{"a":0,"k":100,"ix":5},"r":1,"bm":0,"nm":"Fill 1","mn":"ADBE Vector Graphic - Fill","hd":false},{"ty":"tr","p":{"a":0,"k":[668.433,552.595],"ix":2},"a":{"a":0,"k":[0,0],"ix":1},"s":{"a":0,"k":[100,100],"ix":3},"r":{"a":0,"k":0,"ix":6},"o":{"a":0,"k":100,"ix":7},"sk":{"a":0,"k":0,"ix":4},"sa":{"a":0,"k":0,"ix":5},"nm":"Transform"}],"nm":"Group 6","np":2,"cix":2,"bm":0,"ix":6,"mn":"ADBE Vector Group","hd":false}],"ip":0,"op":48,"st":0,"bm":0},{"ddd":0,"ind":6,"ty":4,"nm":"Eyebrows","parent":3,"sr":1,"ks":{"o":{"a":0,"k":100,"ix":11},"r":{"a":0,"k":0,"ix":10},"p":{"a":1,"k":[{"i":{"x":0.833,"y":0.833},"o":{"x":0.333,"y":0},"t":0,"s":[511.998,420.469,0],"to":[0,3.333,0],"ti":[0,6.667,0]},{"i":{"x":0.667,"y":1},"o":{"x":0.167,"y":0.167},"t":2,"s":[511.998,440.469,0],"to":[0,-6.667,0],"ti":[0,10,0]},{"i":{"x":0.667,"y":0.667},"o":{"x":0.333,"y":0.333},"t":10,"s":[511.998,380.469,0],"to":[0,0,0],"ti":[0,0,0]},{"i":{"x":0,"y":1},"o":{"x":0.333,"y":0},"t":27,"s":[511.998,380.469,0],"to":[0,6.667,0],"ti":[0,-6.667,0]},{"t":39,"s":[511.998,420.469,0]}],"ix":2},"a":{"a":0,"k":[511.998,420.469,0],"ix":1},"s":{"a":0,"k":[100,100,100],"ix":6}},"ao":0,"shapes":[{"ty":"gr","it":[{"ind":0,"ty":"sh","ix":1,"ks":{"a":0,"k":{"i":[[93.228,25.979],[-45.966,-6.956]],"o":[[-61.353,-17.106],[81.437,12.33]],"v":[[5.323,-18.636],[-31.419,18.978]],"c":true},"ix":2},"nm":"Path 1","mn":"ADBE Vector Shape - Group","hd":false},{"ty":"fl","c":{"a":0,"k":[0.709803938866,0.40000000596,0.478431373835,1],"ix":4},"o":{"a":0,"k":100,"ix":5},"r":1,"bm":0,"nm":"Fill 1","mn":"ADBE Vector Graphic - Fill","hd":false},{"ty":"tr","p":{"a":0,"k":[666.597,420.469],"ix":2},"a":{"a":0,"k":[0,0],"ix":1},"s":{"a":0,"k":[100,100],"ix":3},"r":{"a":0,"k":0,"ix":6},"o":{"a":0,"k":100,"ix":7},"sk":{"a":0,"k":0,"ix":4},"sa":{"a":0,"k":0,"ix":5},"nm":"Transform"}],"nm":"Group 1","np":2,"cix":2,"bm":0,"ix":1,"mn":"ADBE Vector Group","hd":false},{"ty":"gr","it":[{"ind":0,"ty":"sh","ix":1,"ks":{"a":0,"k":{"i":[[61.365,-17.106],[-81.438,12.33]],"o":[[-93.216,25.979],[45.942,-6.956]],"v":[[-5.328,-18.636],[31.426,18.978]],"c":true},"ix":2},"nm":"Path 1","mn":"ADBE Vector Shape - Group","hd":false},{"ty":"fl","c":{"a":0,"k":[0.709803938866,0.40000000596,0.478431373835,1],"ix":4},"o":{"a":0,"k":100,"ix":5},"r":1,"bm":0,"nm":"Fill 1","mn":"ADBE Vector Graphic - Fill","hd":false},{"ty":"tr","p":{"a":0,"k":[357.396,420.469],"ix":2},"a":{"a":0,"k":[0,0],"ix":1},"s":{"a":0,"k":[100,100],"ix":3},"r":{"a":0,"k":0,"ix":6},"o":{"a":0,"k":100,"ix":7},"sk":{"a":0,"k":0,"ix":4},"sa":{"a":0,"k":0,"ix":5},"nm":"Transform"}],"nm":"Group 2","np":2,"cix":2,"bm":0,"ix":2,"mn":"ADBE Vector Group","hd":false}],"ip":0,"op":48,"st":0,"bm":0},{"ddd":0,"ind":7,"ty":4,"nm":"pig_face","parent":10,"sr":1,"ks":{"o":{"a":0,"k":100,"ix":11},"r":{"a":0,"k":0,"ix":10},"p":{"a":1,"k":[{"i":{"x":0.667,"y":1},"o":{"x":0.333,"y":0},"t":0,"s":[6.001,-231.882,0],"to":[0,-3.333,0],"ti":[0,0,0]},{"i":{"x":0.667,"y":1},"o":{"x":0.333,"y":0},"t":4,"s":[6.001,-251.882,0],"to":[0,0,0],"ti":[0,-2,0]},{"i":{"x":0.667,"y":1},"o":{"x":0.333,"y":0},"t":12,"s":[6.001,-231.882,0],"to":[0,2,0],"ti":[0,0,0]},{"i":{"x":0.667,"y":1},"o":{"x":0.333,"y":0},"t":16,"s":[6.001,-239.882,0],"to":[0,0,0],"ti":[0,-1.333,0]},{"t":32,"s":[6.001,-231.882,0]}],"ix":2},"a":{"a":0,"k":[0,0,0],"ix":1},"s":{"a":0,"k":[100,100,100],"ix":6}},"ao":0,"shapes":[{"ty":"gr","it":[{"ind":0,"ty":"sh","ix":1,"ks":{"a":0,"k":{"i":[[-43.969,276.01],[262.253,0],[-15.834,-99.947]],"o":[[16.016,-99.947],[-262.228,0],[43.776,276.319]],"v":[[323.798,95.053],[-0.001,-302.176],[-323.837,95.053]],"c":true},"ix":2},"nm":"Path 1","mn":"ADBE Vector Shape - Group","hd":false},{"ty":"gf","o":{"a":0,"k":100,"ix":10},"r":1,"bm":0,"g":{"p":3,"k":{"a":0,"k":[0,1,0.62,0.71,0.406,1,0.7,0.771,1,1,0.78,0.831],"ix":9}},"s":{"a":0,"k":[-0.001,298.47],"ix":5},"e":{"a":0,"k":[-0.001,-340.893],"ix":6},"t":1,"nm":"Pigf04","mn":"ADBE Vector Graphic - G-Fill","hd":false},{"ty":"tr","p":{"a":0,"k":[0,0],"ix":2},"a":{"a":0,"k":[0,0],"ix":1},"s":{"a":0,"k":[100,100],"ix":3},"r":{"a":0,"k":0,"ix":6},"o":{"a":0,"k":100,"ix":7},"sk":{"a":0,"k":0,"ix":4},"sa":{"a":0,"k":0,"ix":5},"nm":"Transform"}],"nm":"Group 1","np":2,"cix":2,"bm":0,"ix":1,"mn":"ADBE Vector Group","hd":false}],"ip":0,"op":48,"st":0,"bm":0},{"ddd":0,"ind":8,"ty":4,"nm":"Ear_Back_R","parent":1,"sr":1,"ks":{"o":{"a":0,"k":100,"ix":11},"r":{"a":0,"k":0,"ix":10},"p":{"a":0,"k":[50.836,-39.637,0],"ix":2},"a":{"a":0,"k":[0,0,0],"ix":1},"s":{"a":0,"k":[100,100,100],"ix":6}},"ao":0,"shapes":[{"ty":"gr","it":[{"ind":0,"ty":"sh","ix":1,"ks":{"a":0,"k":{"i":[[0,0],[0,0],[-39.162,1.417]],"o":[[-105.902,39.472],[-21.792,-27.716],[108.749,-3.977]],"v":[[78.105,-29.802],[-63.438,79.479],[-46.127,-79.268]],"c":true},"ix":2},"nm":"Path 1","mn":"ADBE Vector Shape - Group","hd":false},{"ty":"gf","o":{"a":0,"k":100,"ix":10},"r":1,"bm":0,"g":{"p":3,"k":{"a":0,"k":[0,1,0.561,0.659,0.41,0.925,0.48,0.578,0.636,0.851,0.4,0.498],"ix":9}},"s":{"a":0,"k":[-55.087,7.768],"ix":5},"e":{"a":0,"k":[90.939,-21.435],"ix":6},"t":1,"nm":"Pigf05","mn":"ADBE Vector Graphic - G-Fill","hd":false},{"ty":"tr","p":{"a":0,"k":[0,0],"ix":2},"a":{"a":0,"k":[0,0],"ix":1},"s":{"a":0,"k":[100,100],"ix":3},"r":{"a":0,"k":0,"ix":6},"o":{"a":0,"k":100,"ix":7},"sk":{"a":0,"k":0,"ix":4},"sa":{"a":0,"k":0,"ix":5},"nm":"Transform"}],"nm":"Shape","np":2,"cix":2,"bm":0,"ix":1,"mn":"ADBE Vector Group","hd":false}],"ip":0,"op":48,"st":0,"bm":0},{"ddd":0,"ind":9,"ty":4,"nm":"Ear_Back_L","parent":2,"sr":1,"ks":{"o":{"a":0,"k":100,"ix":11},"r":{"a":0,"k":0,"ix":10},"p":{"a":0,"k":[-50.837,-39.637,0],"ix":2},"a":{"a":0,"k":[0,0,0],"ix":1},"s":{"a":0,"k":[100,100,100],"ix":6}},"ao":0,"shapes":[{"ty":"gr","it":[{"ind":0,"ty":"sh","ix":1,"ks":{"a":0,"k":{"i":[[0,0],[0,0],[39.163,1.417]],"o":[[105.904,39.472],[21.791,-27.716],[-108.748,-3.977]],"v":[[-78.105,-29.802],[63.439,79.479],[46.127,-79.268]],"c":true},"ix":2},"nm":"Path 1","mn":"ADBE Vector Shape - Group","hd":false},{"ty":"gf","o":{"a":0,"k":100,"ix":10},"r":1,"bm":0,"g":{"p":3,"k":{"a":0,"k":[0,1,0.561,0.659,0.41,0.925,0.48,0.578,0.636,0.851,0.4,0.498],"ix":9}},"s":{"a":0,"k":[-78.945,-0.232],"ix":5},"e":{"a":0,"k":[77.265,-0.232],"ix":6},"t":1,"nm":"Pigf06","mn":"ADBE Vector Graphic - G-Fill","hd":false},{"ty":"tr","p":{"a":0,"k":[0,0],"ix":2},"a":{"a":0,"k":[0,0],"ix":1},"s":{"a":0,"k":[100,100],"ix":3},"r":{"a":0,"k":0,"ix":6},"o":{"a":0,"k":100,"ix":7},"sk":{"a":0,"k":0,"ix":4},"sa":{"a":0,"k":0,"ix":5},"nm":"Transform"}],"nm":"Shape","np":2,"cix":2,"bm":0,"ix":1,"mn":"ADBE Vector Group","hd":false}],"ip":0,"op":48,"st":0,"bm":0},{"ddd":0,"ind":10,"ty":3,"nm":"Head_CTRL","sr":1,"ks":{"o":{"a":0,"k":100,"ix":11},"r":{"a":0,"k":0,"ix":10},"p":{"a":1,"k":[{"i":{"x":0,"y":1},"o":{"x":0.333,"y":0},"t":0,"s":[512.001,774.118,0],"to":[0,-3.24,0],"ti":[0,0,0]},{"i":{"x":0.667,"y":1},"o":{"x":0.333,"y":0},"t":4,"s":[512.001,754.677,0],"to":[0,0,0],"ti":[0,-1.953,0]},{"i":{"x":0,"y":1},"o":{"x":0.333,"y":0},"t":12,"s":[512.001,774.118,0],"to":[0,1.953,0],"ti":[0,0,0]},{"i":{"x":0,"y":1},"o":{"x":0.333,"y":0},"t":16,"s":[512.001,766.397,0],"to":[0,0,0],"ti":[0,-1.287,0]},{"t":32,"s":[512.001,774.118,0]}],"ix":2},"a":{"a":0,"k":[0,0,0],"ix":1},"s":{"a":1,"k":[{"i":{"x":[0.833,0.833,0.833],"y":[0.833,0.833,1]},"o":{"x":[0.333,0.333,0.333],"y":[0,0,0]},"t":0,"s":[100,100,100]},{"i":{"x":[0.667,0.667,0.667],"y":[1,1,1]},"o":{"x":[0.167,0.167,0.167],"y":[0.167,0.167,0]},"t":2,"s":[103,97,100]},{"i":{"x":[0.667,0.667,0.667],"y":[1,1,1]},"o":{"x":[0.333,0.333,0.333],"y":[0,0,0]},"t":7,"s":[100,100,100]},{"i":{"x":[0.833,0.833,0.833],"y":[0.833,0.833,1]},"o":{"x":[0.333,0.333,0.333],"y":[0,0,0]},"t":11,"s":[100,100,100]},{"i":{"x":[0.667,0.667,0.667],"y":[1,1,1]},"o":{"x":[0.167,0.167,0.167],"y":[0.167,0.167,0]},"t":13,"s":[103,97,100]},{"t":18,"s":[100,100,100]}],"ix":6}},"ao":0,"ef":[{"ty":5,"nm":"Controller","np":13,"mn":"Pseudo/DUIK controller","ix":1,"en":1,"ef":[{"ty":6,"nm":"Icon","mn":"Pseudo/DUIK controller-0001","ix":1,"v":0},{"ty":2,"nm":"Color","mn":"Pseudo/DUIK controller-0002","ix":2,"v":{"a":0,"k":[0.92549020052,0.0941176489,0.0941176489,1],"ix":2}},{"ty":3,"nm":"Position","mn":"Pseudo/DUIK controller-0003","ix":3,"v":{"a":0,"k":[0,0],"ix":3}},{"ty":0,"nm":"Size","mn":"Pseudo/DUIK controller-0004","ix":4,"v":{"a":0,"k":100,"ix":4}},{"ty":0,"nm":"Orientation","mn":"Pseudo/DUIK controller-0005","ix":5,"v":{"a":0,"k":0,"ix":5}},{"ty":0,"nm":"Opacity","mn":"Pseudo/DUIK controller-0006","ix":6,"v":{"a":0,"k":100,"ix":6}},{"ty":6,"nm":"","mn":"Pseudo/DUIK controller-0007","ix":7,"v":0},{"ty":6,"nm":"Anchor","mn":"Pseudo/DUIK controller-0008","ix":8,"v":0},{"ty":2,"nm":"Color","mn":"Pseudo/DUIK controller-0009","ix":9,"v":{"a":0,"k":[0,0,0,1],"ix":9}},{"ty":0,"nm":"Size","mn":"Pseudo/DUIK controller-0010","ix":10,"v":{"a":0,"k":100,"ix":10}},{"ty":6,"nm":"","mn":"Pseudo/DUIK controller-0011","ix":11,"v":0}]}],"ip":0,"op":48,"st":0,"bm":0}]}],"layers":[{"ddd":0,"ind":1,"ty":0,"nm":"pig_face","refId":"comp_0","sr":1,"ks":{"o":{"a":0,"k":100,"ix":11},"r":{"a":0,"k":0,"ix":10},"p":{"a":0,"k":[512,512,0],"ix":2},"a":{"a":0,"k":[512,512,0],"ix":1},"s":{"a":0,"k":[100,100,100],"ix":6}},"ao":0,"w":1024,"h":1024,"ip":0,"op":48,"st":0,"bm":0}],"markers":[]}